src/VersionUtil.py
src/__init__.py
REMLA23Team09LibProject-0.0.2.dist-info/METADATA
REMLA23Team09LibProject-0.0.2.dist-info/WHEEL
REMLA23Team09LibProject-0.0.2.dist-info/top_level.txt
REMLA23Team09LibProject-0.0.2.dist-info/RECORD
