Metadata-Version: 2.1
Name: REMLA23Team09LibProject
Version: 0.0.2
Summary: A version-aware library
Home-page: https://github.com/remla23-team09/lib
Author: Zhiyong Zhu
Author-email: z13913982280@gmail.com
License: MIT
Requires-Dist: requests
